dj_cleaner/__init__.py
dj_cleaner/__main__.py
dj_cleaner/adapters/__init__.py
dj_cleaner/adapters/interfaces.py
dj_cleaner/adapters/minio_gateway.py
dj_cleaner/adapters/pymysql_gateway.py
dj_cleaner/adapters/toml_controller.py
dj_cleaner/adapters/toml_presenter.py
dj_cleaner/frameworks/__init__.py
dj_cleaner/frameworks/minio_facade.py
dj_cleaner/frameworks/pymysql_facade.py
dj_cleaner/frameworks/toml_cli.py
dj_cleaner/use_cases/__init__.py
dj_cleaner/use_cases/abstract.py
dj_cleaner/use_cases/clean.py
dj_cleaner/use_cases/interfaces.py
datajoint_cleaner-0.1.dist-info/entry_points.txt
datajoint_cleaner-0.1.dist-info/WHEEL
datajoint_cleaner-0.1.dist-info/METADATA
datajoint_cleaner-0.1.dist-info/LICENSE
datajoint_cleaner-0.1.dist-info/RECORD
