Metadata-Version: 2.1
Name: datajoint-cleaner
Version: 0.1
Summary: A tool for cleaning up external DataJoint stores
License: UNKNOWN
Author-email: Christoph Blessing <chris.blessing@protonmail.com>
Requires-Python: >=3.9
Classifier: Programming Language :: Python :: 3
Classifier: Programming Language :: Python :: 3.9
Requires-Dist: minio~=7.0
Requires-Dist: pymysql~=1.0
Requires-Dist: toml~=0.10
Project-URL: homepage, https://github.com/sinzlab/datajoint-cleaner
